searchdatamodels/__init__.py
searchdatamodels/search_classes.py
searchdatamodels/tagline_embedding.py
searchdatamodels/test/__init__.py
searchdatamodels/test/test_search_classes.py
searchdatamodels/test/test_tagline_embedding.py
searchdatamodels-0.0.60.dist-info/METADATA
searchdatamodels-0.0.60.dist-info/WHEEL
searchdatamodels-0.0.60.dist-info/top_level.txt
searchdatamodels-0.0.60.dist-info/RECORD
