Metadata-Version: 2.1
Name: searchdatamodels
Version: 0.0.60
Author: James Baker
Author-email: james@talentium.io
License: MIT
Classifier: Programming Language :: Python :: 3
Classifier: License :: OSI Approved :: MIT License
Classifier: Operating System :: OS Independent
Requires-Dist: annotated-types ==0.5.0
Requires-Dist: appdirs ==1.4.4
Requires-Dist: certifi ==2023.7.22
Requires-Dist: charset-normalizer ==3.2.0
Requires-Dist: click ==8.1.6
Requires-Dist: docker-pycreds ==0.4.0
Requires-Dist: filelock ==3.12.2
Requires-Dist: fsspec ==2023.6.0
Requires-Dist: gitdb ==4.0.10
Requires-Dist: GitPython ==3.1.32
Requires-Dist: huggingface-hub ==0.16.4
Requires-Dist: idna ==3.4
Requires-Dist: Jinja2 ==3.1.2
Requires-Dist: joblib ==1.3.2
Requires-Dist: MarkupSafe ==2.1.3
Requires-Dist: mpmath ==1.3.0
Requires-Dist: networkx ==3.1
Requires-Dist: nltk ==3.8.1
Requires-Dist: numpy ==1.25.2
Requires-Dist: packaging ==23.1
Requires-Dist: pathtools ==0.1.2
Requires-Dist: Pillow ==10.0.0
Requires-Dist: protobuf >=3.19.5
Requires-Dist: psutil ==5.9.5
Requires-Dist: pydantic ==1.10.8
Requires-Dist: pydantic-core ==2.6.0
Requires-Dist: python-dotenv >=1.0.0
Requires-Dist: PyYAML ==6.0.1
Requires-Dist: regex ==2023.8.8
Requires-Dist: requests ==2.31.0
Requires-Dist: safetensors ==0.3.2
Requires-Dist: scikit-learn ==1.3.0
Requires-Dist: scipy ==1.11.1
Requires-Dist: sentence-transformers ==2.2.2
Requires-Dist: sentencepiece ==0.1.99
Requires-Dist: sentry-sdk ==1.29.2
Requires-Dist: setproctitle ==1.3.2
Requires-Dist: six ==1.16.0
Requires-Dist: smmap ==5.0.0
Requires-Dist: strsimpy ==0.2.1
Requires-Dist: sympy ==1.12
Requires-Dist: threadpoolctl ==3.2.0
Requires-Dist: tokenizers ==0.13.3
Requires-Dist: torch ==2.0.1
Requires-Dist: torchvision ==0.15.2
Requires-Dist: tqdm ==4.66.1
Requires-Dist: transformers ==4.31.0
Requires-Dist: typing-extensions ==4.7.1
Requires-Dist: urllib3
Requires-Dist: deepl >=1.15.0
Requires-Dist: langdetect >=1.0.9
